llmunchies/__init__.py
llmunchies/adapter_anthropic.py
llmunchies/adapter_openai.py
llmunchies/memory.py
llmunchies-0.2.0.dist-info/METADATA
llmunchies-0.2.0.dist-info/WHEEL
llmunchies-0.2.0.dist-info/top_level.txt
llmunchies-0.2.0.dist-info/RECORD
