Metadata-Version: 2.4
Name: llmunchies
Version: 0.2.0
Summary: A lightweight, model-agnostic context engine for LLMs. Feed your model tasty context.
Author: LLMunchies Team
Project-URL: Homepage, https://github.com/kabiru-js/llmunchies.git
Project-URL: Issues, https://github.com/your-username/llmunchies/issues
Keywords: llm,context,memory,prompt,gpt,claude,ai,middleware
Classifier: Development Status :: 4 - Beta
Classifier: Intended Audience :: Developers
Classifier: License :: OSI Approved :: MIT License
Classifier: Programming Language :: Python :: 3
Classifier: Programming Language :: Python :: 3.8
Classifier: Programming Language :: Python :: 3.9
Classifier: Programming Language :: Python :: 3.10
Classifier: Programming Language :: Python :: 3.11
Classifier: Programming Language :: Python :: 3.12
Classifier: Topic :: Software Development :: Libraries :: Python Modules
Classifier: Topic :: Scientific/Engineering :: Artificial Intelligence
Requires-Python: >=3.8
Requires-Dist: tiktoken>=0.5.0
